Workbook

Sheet OLD
A1: Industry | B1: Sector | C1: SCS Sectors | D1: Economic Model | E1: Tier-1 KPI Template | F1: Tier-2 KPI Template - Narrower - for deep research
A2: Advertising/Marketing services | B2: Commercial services | C2: Other | D2: Fee Based Services | E2: Infrastructure Template | F2: Commercial Services
A3: Aerospace & defense | B3: Electronic technology | C3: Other | D3: Industrial Manufacturing | E3: Infrastructure Template | F3: Defence
A4: Agricultural commodities/Milling | B4: Process industries | C4: Other | D4: Commodity Producer | E4: Commodity Template | F4: Agri Processing
A5: Air freight/Couriers | B5: Transportation | C5: Other | D5: Asset Utilization | E5: Asset Utilization Template | F5: Logistics
A6: Airlines | B6: Transportation | C6: Other | D6: Asset Utilization | E6: Asset Utilization Template | F6: Logistics
A7: Alternative power generation | B7: Utilities | C7: Other | D7: Utility | E7: Utility Template | F7: Renewables
A8: Aluminum | B8: Non-energy minerals | C8: Cement Chemical Metal | D8: Commodity Producer | E8: Commodity Template | F8: Metals & Mining
A9: Apparel/Footwear | B9: Consumer non-durables | C9: Consumption & FMCG | D9: Brand Franchise | E9: Consumer Brand Template | F9: FMCG/Consumer Brands
A10: Apparel/Footwear retail | B10: Retail trade | C10: Other | D10: Store Economics | E10: Retail Template | F10: Retail
A11: Auto parts: OEM | B11: Producer manufacturing | C11: Auto | D11: Manufacturing | E11: Manufacturing Template | F11: Auto Ancillary
A12: Automotive aftermarket | B12: Consumer durables | C12: Auto | D12: Manufacturing | E12: Manufacturing Template | F12: Auto Ancillary
... A131: Wireless telecommunications | B131: Communications | C131: Other | D131: Network Utility | E131: Utility Template | F131: Telecom

Sheet Industry Mapping
A1: 190_Industry | B1: Industry | C1: Sectors | D1: SCS Sectors | E1: Economic Model | F1: Template
A2: 2/3 Wheelers | B2: Miscellaneous | C2: =VLOOKUP(B2,OLD!$A$2:$C$131,2,) -> Miscellaneous | D2: =VLOOKUP(B2,OLD!$A$2:$C$131,3,FALSE) -> Other | E2: =VLOOKUP(B2,OLD!$A$2:$E$131,4,TRUE) -> Diversified | F2: =VLOOKUP(B2,OLD!$A$2:$E$131,5,TRUE) -> Capital Allocation Template
A3: Abrasives & Bearings | B3: Miscellaneous | C3: =VLOOKUP(B3,OLD!$A$2:$C$131,2,) -> Miscellaneous | D3: =VLOOKUP(B3,OLD!$A$2:$C$131,3,FALSE) -> Other | E3: =VLOOKUP(B3,OLD!$A$2:$E$131,4,TRUE) -> Diversified | F3: =VLOOKUP(B3,OLD!$A$2:$E$131,5,TRUE) -> Capital Allocation Template
A4: Advertising & Media Agencies | B4: Broadcasting | C4: =VLOOKUP(B4,OLD!$A$2:$C$131,2,) -> Consumer services | D4: =VLOOKUP(B4,OLD!$A$2:$C$131,3,FALSE) -> Other | E4: =VLOOKUP(B4,OLD!$A$2:$E$131,4,TRUE) -> Media | F4: =VLOOKUP(B4,OLD!$A$2:$E$131,5,TRUE) -> Asset Utilization Template
A5: Aerospace & Defense | B5: Aerospace & defense | C5: =VLOOKUP(B5,OLD!$A$2:$C$131,2,) -> Electronic technology | D5: =VLOOKUP(B5,OLD!$A$2:$C$131,3,FALSE) -> Other | E5: =VLOOKUP(B5,OLD!$A$2:$E$131,4,TRUE) -> Industrial Manufacturing | F5: =VLOOKUP(B5,OLD!$A$2:$E$131,5,TRUE) -> Infrastructure Template
A6: Airline | B6: Airlines | C6: =VLOOKUP(B6,OLD!$A$2:$C$131,2,) -> Transportation | D6: =VLOOKUP(B6,OLD!$A$2:$C$131,3,FALSE) -> Other | E6: =VLOOKUP(B6,OLD!$A$2:$E$131,4,TRUE) -> Asset Utilization | F6: =VLOOKUP(B6,OLD!$A$2:$E$131,5,TRUE) -> Asset Utilization Template
A7: Airport & Airport services | B7: Miscellaneous | C7: =VLOOKUP(B7,OLD!$A$2:$C$131,2,) -> Miscellaneous | D7: =VLOOKUP(B7,OLD!$A$2:$C$131,3,FALSE) -> Other | E7: =VLOOKUP(B7,OLD!$A$2:$E$131,4,TRUE) -> Diversified | F7: =VLOOKUP(B7,OLD!$A$2:$E$131,5,TRUE) -> Capital Allocation Template
A8: Aluminium | B8: Other metals/Minerals | C8: =VLOOKUP(B8,OLD!$A$2:$C$131,2,) -> Non-energy minerals | D8: =VLOOKUP(B8,OLD!$A$2:$C$131,3,FALSE) -> Cement Chemical Metal | E8: =VLOOKUP(B8,OLD!$A$2:$E$131,4,TRUE) -> Commodity Producer | F8: =VLOOKUP(B8,OLD!$A$2:$E$131,5,TRUE) -> Commodity Template
A9: Aluminium, Copper & Zinc Products | B9: Other metals/Minerals | C9: =VLOOKUP(B9,OLD!$A$2:$C$131,2,) -> Non-energy minerals | D9: =VLOOKUP(B9,OLD!$A$2:$C$131,3,FALSE) -> Cement Chemical Metal | E9: =VLOOKUP(B9,OLD!$A$2:$E$131,4,TRUE) -> Commodity Producer | F9: =VLOOKUP(B9,OLD!$A$2:$E$131,5,TRUE) -> Commodity Template
A10: Amusement Parks/ Other Recreation | B10: Miscellaneous | C10: =VLOOKUP(B10,OLD!$A$2:$C$131,2,) -> Miscellaneous | D10: =VLOOKUP(B10,OLD!$A$2:$C$131,3,FALSE) -> Other | E10: =VLOOKUP(B10,OLD!$A$2:$E$131,4,TRUE) -> Diversified | F10: =VLOOKUP(B10,OLD!$A$2:$E$131,5,TRUE) -> Capital Allocation Template
A11: Animal Feed | B11: Miscellaneous | C11: =VLOOKUP(B11,OLD!$A$2:$C$131,2,) -> Miscellaneous | D11: =VLOOKUP(B11,OLD!$A$2:$C$131,3,FALSE) -> Other | E11: =VLOOKUP(B11,OLD!$A$2:$E$131,4,TRUE) -> Diversified | F11: =VLOOKUP(B11,OLD!$A$2:$E$131,5,TRUE) -> Capital Allocation Template
A12: Asset Management Company | B12: Investment managers | C12: =VLOOKUP(B12,OLD!$A$2:$C$131,2,) -> Finance | D12: =VLOOKUP(B12,OLD!$A$2:$C$131,3,FALSE) -> Finance | E12: =VLOOKUP(B12,OLD!$A$2:$E$131,4,TRUE) -> Fee Based Financial | F12: =VLOOKUP(B12,OLD!$A$2:$E$131,5,TRUE) -> Asset Management Template
A13: Auto Components & Equipments | B13: Auto parts: OEM | C13: =VLOOKUP(B13,OLD!$A$2:$C$131,2,) -> Producer manufacturing | D13: =VLOOKUP(B13,OLD!$A$2:$C$131,3,FALSE) -> Auto | E13: =VLOOKUP(B13,OLD!$A$2:$E$131,4,TRUE) -> Manufacturing | F13: =VLOOKUP(B13,OLD!$A$2:$E$131,5,TRUE) -> Manufacturing Template
... A191: Zinc | B191: Other metals/Minerals | C191: =VLOOKUP(B191,OLD!$A$2:$C$131,2,) -> Non-energy minerals | D191: =VLOOKUP(B191,OLD!$A$2:$C$131,3,FALSE) -> Cement Chemical Metal | E191: =VLOOKUP(B191,OLD!$A$2:$E$131,4,TRUE) -> Commodity Producer | F191: =VLOOKUP(B191,OLD!$A$2:$E$131,5,TRUE) -> Commodity Template
